ConsoleOutput/ConsoleOutput.py
ConsoleOutput/__init__.py
ConsoleOutput-1.2.0.dist-info/LICENSE
ConsoleOutput-1.2.0.dist-info/METADATA
ConsoleOutput-1.2.0.dist-info/WHEEL
ConsoleOutput-1.2.0.dist-info/top_level.txt
ConsoleOutput-1.2.0.dist-info/RECORD
